{
  "generated_date": "2025-12-15T07:00:14.452349",
  "day_of_week": "Monday",
  "includes_services": false,
  "articles": [
    {
      "headline": "Google Expands Hyperscale Data Center Footprint in Indiana's Franklin Township",
      "content": "Tech giant Google has secured approval for a new data center project in Franklin Township, Indiana, signaling continued investment in the state's growing digital infrastructure landscape. While specific capacity details remain undisclosed, the project represents another strategic expansion of Google's extensive network of hyperscale computing facilities. The development underscores the region's increasing attractiveness for major cloud and technology companies seeking robust locations for mission-critical data center deployments."
    },
    {
      "headline": "Ann Arbor Emerges as Potential Data Center Hub with New Proposed Project",
      "content": "Michigan's tech landscape could be expanding with a new data center proposal in Ann Arbor, signaling growing interest in the region's digital infrastructure potential. While specific details about the project's operator and total capacity remain undisclosed, the proposed development suggests continued momentum in the Midwest's evolving data center market. The Ann Arbor project could represent an emerging opportunity for regional economic growth and technological investment."
    }
  ]
}