{
  "generated_date": "2025-12-14T07:00:13.754822",
  "day_of_week": "Sunday",
  "includes_services": false,
  "articles": [
    {
      "headline": "Michigan Tech Hub Ann Arbor Eyes Major Data Center Infrastructure Expansion",
      "content": "A significant data center project is being considered for development in Ann Arbor, potentially boosting the region's growing technology ecosystem. The proposed facility represents a strategic investment in Michigan's digital infrastructure, signaling continued momentum in the state's efforts to attract data center and cloud computing investments. While specific details about capacity and the project's developer remain undisclosed, the initiative underscores Ann Arbor's emerging potential as a competitive data center market."
    },
    {
      "headline": "Georgia Data Center Expands Digital Infrastructure in Metro Atlanta Region",
      "content": "A new operational data center has emerged in Fayetteville, bolstering the region's growing digital ecosystem. The facility represents a strategic addition to the metro Atlanta area's expanding data infrastructure landscape, potentially serving enterprise and cloud computing clients seeking robust regional connectivity. While specific operational details remain limited, the project signals continued investment in Georgia's data center market."
    }
  ]
}